projpicker_gui/VERSION
projpicker_gui/__init__.py
projpicker_gui/map.html
projpicker_gui/projpicker_gui.py
projpicker_gui-0.1.0.dev10.dist-info/LICENSE
projpicker_gui-0.1.0.dev10.dist-info/METADATA
projpicker_gui-0.1.0.dev10.dist-info/WHEEL
projpicker_gui-0.1.0.dev10.dist-info/entry_points.txt
projpicker_gui-0.1.0.dev10.dist-info/top_level.txt
projpicker_gui-0.1.0.dev10.dist-info/RECORD
