Metadata-Version: 2.1
Name: projpicker-gui
Version: 0.1.0.dev10
Summary: ProjPicker GUI
Home-page: https://github.com/HuidaeCho/projpicker-gui
Author: Owen Smith and Huidae Cho
Author-email: grass4u@gmail.com
License: GPLv3+
Platform: UNKNOWN
Classifier: Programming Language :: Python :: 3
Classifier: License :: OSI Approved :: GNU General Public License v3 or later (GPLv3+)
Classifier: Operating System :: OS Independent
Requires-Python: >=3
License-File: LICENSE
